{"kind":"identitytoolkit#DownloadAccountResponse","users":[{"localId":"95nPW2IHflNjS8ZHMHGOwHwW6ohG","createdAt":"1726079850047","lastLoginAt":"1726079850047","displayName":"admintest3","passwordHash":"fakeHash:salt=fakeSaltEbIDiZPTO5C2LUHfFzpU:password=admin12345","salt":"fakeSaltEbIDiZPTO5C2LUHfFzpU","passwordUpdatedAt":1728541335122,"providerUserInfo":[{"providerId":"password","email":"admintest3@gmail.com","federatedId":"admintest3@gmail.com","rawId":"admintest3@gmail.com","displayName":"admintest3"}],"validSince":"1728541335","email":"admintest3@gmail.com","emailVerified":false,"disabled":false},{"localId":"BI9p9nUnmr5ME7aR9jTau9iJc6OH","createdAt":"1725601470745","lastLoginAt":"1725601470745","passwordHash":"fakeHash:salt=fakeSaltaNPSSIlqoaZfGraC8t88:password=@Test1234","salt":"fakeSaltaNPSSIlqoaZfGraC8t88","passwordUpdatedAt":1728541335122,"providerUserInfo":[{"providerId":"password","email":"kmkm@gmail.com","federatedId":"kmkm@gmail.com","rawId":"kmkm@gmail.com"}],"validSince":"1728541335","email":"kmkm@gmail.com","emailVerified":false,"disabled":false},{"localId":"IkhduzFJfuntOSJfRLAtD8Y9UqNp","createdAt":"1726079830641","lastLoginAt":"1726079830641","displayName":"admintest2","passwordHash":"fakeHash:salt=fakeSaltehhULnjEfscFxqXxVglG:password=admin12345","salt":"fakeSaltehhULnjEfscFxqXxVglG","passwordUpdatedAt":1728541335122,"providerUserInfo":[{"providerId":"password","email":"admintest2@gmail.com","federatedId":"admintest2@gmail.com","rawId":"admintest2@gmail.com","displayName":"admintest2"}],"validSince":"1728541335","email":"admintest2@gmail.com","emailVerified":false,"disabled":false},{"localId":"NuAWQS1HF1iQrNs0baaAC3A9y8ES","createdAt":"1724326236284","lastLoginAt":"1728585521851","passwordHash":"fakeHash:salt=fakeSaltpRMcCrpQQzIHEjugCM5r:password=@Text1234","salt":"fakeSaltpRMcCrpQQzIHEjugCM5r","passwordUpdatedAt":1728541335122,"providerUserInfo":[{"providerId":"password","email":"test@gmail.com","federatedId":"test@gmail.com","rawId":"test@gmail.com"}],"validSince":"1728541335","email":"test@gmail.com","emailVerified":false,"disabled":false,"lastRefreshAt":"2024-10-10T18:38:41.851Z"},{"localId":"VDCQLNDXmtYlZ4aW554pGs4vZhDb","createdAt":"1726079838422","lastLoginAt":"1728586769477","displayName":"admintest1","passwordHash":"fakeHash:salt=fakeSaltr3jA5wPQxEaRyxC6UNGh:password=admin12345","salt":"fakeSaltr3jA5wPQxEaRyxC6UNGh","passwordUpdatedAt":1728541335122,"providerUserInfo":[{"providerId":"password","email":"admintest1@gmail.com","federatedId":"admintest1@gmail.com","rawId":"admintest1@gmail.com","displayName":"admintest1"}],"validSince":"1728541335","email":"admintest1@gmail.com","emailVerified":false,"disabled":false,"lastRefreshAt":"2024-10-10T18:59:29.477Z"},{"localId":"wJmmw7JZ9aj1Rk199Di290YbuNvs","createdAt":"1726234927940","lastLoginAt":"1728586587533","passwordHash":"fakeHash:salt=fakeSaltDyvm5BMpBfPC519LcmN0:password=@Test1234","salt":"fakeSaltDyvm5BMpBfPC519LcmN0","passwordUpdatedAt":1728541335122,"providerUserInfo":[{"providerId":"password","email":"supapich161247@gmail.com","federatedId":"supapich161247@gmail.com","rawId":"supapich161247@gmail.com"}],"validSince":"1728541335","email":"supapich161247@gmail.com","emailVerified":false,"disabled":false,"lastRefreshAt":"2024-10-10T18:56:27.533Z"}]}